src/__init__.py
src/flea_scope.py
src/serial_terminal.py
src/trigger_config.py
pyfleascope_dfreier-0.0.1.dist-info/METADATA
pyfleascope_dfreier-0.0.1.dist-info/WHEEL
pyfleascope_dfreier-0.0.1.dist-info/RECORD
