Metadata-Version: 2.4
Name: pyfleascope_dfreier
Version: 0.0.1
Summary: A python package for instrumenting the FleaScope
Project-URL: Homepage, https://github.com/daniel-freiermuth/pyfleascope
Project-URL: Issues, https://github.com/daniel-freiermuth/pyfleascope/issues
Author-email: "D. Freiermuth" <author@example.com>
License-Expression: MIT
Classifier: Operating System :: OS Independent
Classifier: Programming Language :: Python :: 3
Requires-Python: >=3.9
